gltf/__init__.py
gltf/_converter.py
gltf/_converter_maps.py
gltf/_loader.py
gltf/cli.py
gltf/parseutils.py
gltf/version.py
gltf/viewer.py
panda3d_gltf-1.2.0.dist-info/LICENSE.txt
panda3d_gltf-1.2.0.dist-info/METADATA
panda3d_gltf-1.2.0.dist-info/WHEEL
panda3d_gltf-1.2.0.dist-info/entry_points.txt
panda3d_gltf-1.2.0.dist-info/top_level.txt
panda3d_gltf-1.2.0.dist-info/RECORD
