Metadata-Version: 2.1
Name: panda3d-gltf
Version: 1.2.0
Summary: glTF utilities for Panda3D
Author: Mitchell Stokes
License: BSD-3-Clause
Project-URL: homepage, https://github.com/Moguri/panda3d-gltf
Keywords: panda3d,gltf
Classifier: Development Status :: 5 - Production/Stable
Classifier: License :: OSI Approved :: BSD License
Classifier: Programming Language :: Python :: 3
Requires-Python: >=3.8
License-File: LICENSE.txt
Requires-Dist: panda3d>=1.10.8
Requires-Dist: panda3d-simplepbr>=0.6
Provides-Extra: test
Requires-Dist: pytest; extra == "test"
Requires-Dist: pylint~=3.1.0; extra == "test"
Requires-Dist: pytest-pylint; extra == "test"
